Metadata-Version: 1.0
Name: sbad-distributions
Version: 0.1
Summary: Gaussian and Binomial distributions
Home-page: UNKNOWN
Author: Sergio Badillo
Author-email: sbadilloworks@gmail.com
License: UNKNOWN
Platform: UNKNOWN
